gitlab_stats/__init__.py
gitlab_stats/cli.py
gitlab_stats/utils.py
gitlab_stats/wrapper.py
tests/__init__.py
tests/__init__.pyc
tests/mock_server.py
tests/test_cli.py
tests/test_cli.pyc
tests/test_utils.py
tests/test_wrapper.py
tests/.pytest_cache/v/cache/lastfailed
tests/.pytest_cache/v/cache/nodeids
tests/__pycache__/__init__.cpython-36.pyc
tests/__pycache__/__init__.cpython-37.pyc
tests/__pycache__/mock_server.cpython-36.pyc
tests/__pycache__/mock_server.cpython-37.pyc
tests/__pycache__/test_cli.cpython-36-PYTEST.pyc
tests/__pycache__/test_cli.cpython-36.pyc
tests/__pycache__/test_cli.cpython-37-pytest-5.0.1.pyc
tests/__pycache__/test_utils.cpython-36-PYTEST.pyc
tests/__pycache__/test_utils.cpython-36.pyc
tests/__pycache__/test_utils.cpython-37-pytest-5.0.1.pyc
tests/__pycache__/test_wrapper.cpython-36-PYTEST.pyc
tests/__pycache__/test_wrapper.cpython-36.pyc
tests/__pycache__/test_wrapper.cpython-37-pytest-5.0.1.pyc
gitlab_stats-1.2.1.dist-info/LICENSE
gitlab_stats-1.2.1.dist-info/METADATA
gitlab_stats-1.2.1.dist-info/WHEEL
gitlab_stats-1.2.1.dist-info/entry_points.txt
gitlab_stats-1.2.1.dist-info/top_level.txt
gitlab_stats-1.2.1.dist-info/RECORD
