Metadata-Version: 2.1
Name: gitlab-stats
Version: 1.2.1
Summary: CLI to get pipeline stats from gitlab API v4 using gitlab project ID
Home-page: https://github.com/Sylhare/gitlab_stats
Author: sylhare
Author-email: sylhare@outlook.com
License: MIT
Keywords: gitlab pipeline stats build
Platform: UNKNOWN
Classifier: Development Status :: 5 - Production/Stable
Classifier: License :: OSI Approved :: MIT License
Classifier: Programming Language :: Python :: 3.6
Requires-Dist: requests
Provides-Extra: test
Requires-Dist: coverage ; extra == 'test'
Requires-Dist: pytest ; extra == 'test'
